setup.py
src/munin.py
src/python_munin.egg-info/PKG-INFO
src/python_munin.egg-info/SOURCES.txt
src/python_munin.egg-info/dependency_links.txt
src/python_munin.egg-info/requires.txt
src/python_munin.egg-info/top_level.txt