Metadata-Version: 1.1
Name: python-munin
Version: 0.3.2
Summary: Framework for writing munin plugins.
Home-page: https://github.com/cooledcoffee/python-munin
Author: Mengchen LEE
Author-email: UNKNOWN
License: UNKNOWN
Platform: UNKNOWN
Classifier: Development Status :: 4 - Beta
Classifier: Intended Audience :: Developers
Classifier: Intended Audience :: System Administrators
Classifier: Operating System :: OS Independent
Classifier: Programming Language :: Python
Classifier: Programming Language :: Python :: 2
Classifier: Programming Language :: Python :: 3
Classifier: Topic :: System :: Monitoring
